<annotation>
	<folder>images</folder>
	<filename>maintenanceWorker_293.jpg</filename>
	<path>D:\code_tools\spiders\Dataset\Yelan\images\maintenanceWorker_293.jpg</path>
	<source>
		<database>Unknown</database>
	</source>
	<size>
		<width>592</width>
		<height>500</height>
		<depth>3</depth>
	</size>
	<segmented>0</segmented>
	<object>
		<name>夜兰</name>
		<pose>Unspecified</pose>
		<truncated>0</truncated>
		<difficult>0</difficult>
		<bndbox>
			<xmin>216</xmin>
			<ymin>106</ymin>
			<xmax>497</xmax>
			<ymax>446</ymax>
		</bndbox>
	</object>
</annotation>
